gesture-recognizer/GestureRecognizer.py
gesture-recognizer/__init__.py
gesture-recognizer/test.py
gesture_recognizer/.DS_Store
gesture_recognizer/FistRecognizer.py
gesture_recognizer/GestureRecognizer.py
gesture_recognizer/GestureRecognizer.pyc
gesture_recognizer/__init__.py
gesture_recognizer/aGest.xml
gesture_recognizer/haarcascade_fist.xml
gesture_recognizer/haarcascade_palm.xml
gesture_recognizer/test.py
gesture_recognizer/__pycache__/FistRecognizer.cpython-36.pyc
gesture_recognizer/__pycache__/GestureRecognizer.cpython-36.pyc
gesture_recognizer/__pycache__/__init__.cpython-36.pyc
gesture_recognizer-0.3.11.dist-info/LICENSE.txt
gesture_recognizer-0.3.11.dist-info/METADATA
gesture_recognizer-0.3.11.dist-info/WHEEL
gesture_recognizer-0.3.11.dist-info/top_level.txt
gesture_recognizer-0.3.11.dist-info/RECORD
