Metadata-Version: 2.1
Name: gesture-recognizer
Version: 0.3.11
Summary: A basic gesture recognizer module for a hackathon.
Home-page: https://github.com/calee14/gesture-recognizer
Author: capjedi
Author-email: calee14@s.sfusd.edu
License: MIT
Platform: UNKNOWN
Classifier: Programming Language :: Python :: 3
Classifier: License :: OSI Approved :: MIT License
Classifier: Operating System :: OS Independent
Requires-Dist: opencv-python
Requires-Dist: numpy
